rolltables/__init__.py
rolltables/constants.py
rolltables/priortables.py
rolltables/rolltables.py
rolltables/utils.py
rolltables/data/priortables.json
rolltables/data/rolltables.json
tests/__init__.py
tests/priortables.py
tests/rolltables.py
rolltables-0.2.1.dist-info/LICENCE
rolltables-0.2.1.dist-info/METADATA
rolltables-0.2.1.dist-info/WHEEL
rolltables-0.2.1.dist-info/top_level.txt
rolltables-0.2.1.dist-info/RECORD
