Metadata-Version: 2.1
Name: rolltables
Version: 0.2.1
Summary: Commodity futures roll tables made easy
Home-page: https://github.com/dschenck/rolltables
Author: david.schenck@outlook.com
Author-email: david.schenck@outlook.com
License: UNKNOWN
Platform: UNKNOWN
Classifier: Programming Language :: Python :: 3
Classifier: License :: OSI Approved :: MIT License
Classifier: Operating System :: OS Independent
Requires-Dist: pandas
